LICENSE
README.md
setup.py
zkteco_push/ZKTECO_CONST.py
zkteco_push/ZKTECO_HELPERS.py
zkteco_push/__init__.py
zkteco_push/utils.py
zkteco_push/zkdevice.py
zkteco_push/zklog.py
zkteco_push/zkuser.py
zkteco_push_python_sdk.egg-info/PKG-INFO
zkteco_push_python_sdk.egg-info/SOURCES.txt
zkteco_push_python_sdk.egg-info/dependency_links.txt
zkteco_push_python_sdk.egg-info/requires.txt
zkteco_push_python_sdk.egg-info/top_level.txt