Metadata-Version: 2.1
Name: zkteco-push-python-sdk
Version: 1.0.5
Summary: A Python SDK for ZKTeco Attendance Pull Communication Protocol
Home-page: https://github.com/EtsBIZ4Africa/zkteco-push-python-sdk
Author: Vincent Luba
Author-email: vincent@biz-4-africa.com
Classifier: Programming Language :: Python :: 3
Classifier: License :: OSI Approved :: MIT License
Classifier: Operating System :: OS Independent
Requires-Python: >=3.6
License-File: LICENSE
